DA_Koyeb/__init__.py
DA_Koyeb/health.py
koyeb-0.2.dist-info/METADATA
koyeb-0.2.dist-info/WHEEL
koyeb-0.2.dist-info/top_level.txt
koyeb-0.2.dist-info/RECORD
