Metadata-Version: 2.4
Name: koyeb
Version: 0.2
Summary: A Personal Python package to run apps seamlessly on Koyeb.
Home-page: https://t.me/North_Yankton
Author: Alpha
Author-email: imr@outlook.in
Classifier: Programming Language :: Python :: 3
Classifier: License :: OSI Approved :: MIT License
Classifier: Operating System :: OS Independent
Requires-Python: >=3.6
Requires-Dist: flask
Dynamic: author
Dynamic: author-email
Dynamic: classifier
Dynamic: description
Dynamic: description-content-type
Dynamic: home-page
Dynamic: requires-dist
Dynamic: requires-python
Dynamic: summary
